pycheckpoint/__init__.py
pychequepoint-0.0.3.dist-info/LICENSE
pychequepoint-0.0.3.dist-info/METADATA
pychequepoint-0.0.3.dist-info/WHEEL
pychequepoint-0.0.3.dist-info/top_level.txt
pychequepoint-0.0.3.dist-info/RECORD
