Metadata-Version: 2.1
Name: pychequepoint
Version: 0.0.3
Summary: A simple tool that automate checkpointing. 
Author-email: Yurun Yuan <yurun.yuan@outlook.com>
Project-URL: Homepage, https://github.com/yurun-yuan/pycheckpoint
Project-URL: Issues, https://github.com/yurun-yuan/pycheckpoint/issues
Requires-Python: >=3.8
License-File: LICENSE
Requires-Dist: pandas
